bencode/BTL.py
bencode/__init__.py
bencode_python3-1.0.2.dist-info/DESCRIPTION.rst
bencode_python3-1.0.2.dist-info/METADATA
bencode_python3-1.0.2.dist-info/RECORD
bencode_python3-1.0.2.dist-info/WHEEL
bencode_python3-1.0.2.dist-info/metadata.json
bencode_python3-1.0.2.dist-info/top_level.txt
